treethestima/__init__.py
treethestima-0.1.0.dist-info/LICENSE.txt
treethestima-0.1.0.dist-info/METADATA
treethestima-0.1.0.dist-info/WHEEL
treethestima-0.1.0.dist-info/top_level.txt
treethestima-0.1.0.dist-info/RECORD
