Metadata-Version: 2.1
Name: treethestima
Version: 0.1.0
Summary: A package for using pkl files to calculate frequency percentages
Home-page: https://github.com/yourusername/treethestima
Author: YN
Author-email: morgen@emory.edu.com
License: MIT
Classifier: Programming Language :: Python :: 3
Classifier: License :: OSI Approved :: MIT License
Classifier: Operating System :: OS Independent
Requires-Python: >=3.6
License-File: LICENSE.txt
Requires-Dist: numpy
